siotls/__init__.py
siotls/__main__.py
siotls/asn1types.py
siotls/configuration.py
siotls/connection.py
siotls/iana.py
siotls/language.py
siotls/oid.py
siotls/pem.py
siotls/py.typed
siotls/transcript.py
siotls/utils.py
siotls/wrapper.py
siotls/contents/__init__.py
siotls/contents/alerts.py
siotls/contents/application_data.py
siotls/contents/change_cipher_spec.py
siotls/contents/heartbeat.py
siotls/contents/handshakes/__init__.py
siotls/contents/handshakes/certificate.py
siotls/contents/handshakes/certificate_request.py
siotls/contents/handshakes/certificate_verify.py
siotls/contents/handshakes/client_hello.py
siotls/contents/handshakes/encrypted_extensions.py
siotls/contents/handshakes/end_of_early_data.py
siotls/contents/handshakes/finished.py
siotls/contents/handshakes/key_update.py
siotls/contents/handshakes/new_session_ticket.py
siotls/contents/handshakes/server_hello.py
siotls/contents/handshakes/extensions/__init__.py
siotls/contents/handshakes/extensions/alpn.py
siotls/contents/handshakes/extensions/certificate_authorities.py
siotls/contents/handshakes/extensions/certificate_type.py
siotls/contents/handshakes/extensions/cookie.py
siotls/contents/handshakes/extensions/early_data.py
siotls/contents/handshakes/extensions/heartbeat.py
siotls/contents/handshakes/extensions/key_share.py
siotls/contents/handshakes/extensions/max_fragment_length.py
siotls/contents/handshakes/extensions/oid_filters.py
siotls/contents/handshakes/extensions/padding.py
siotls/contents/handshakes/extensions/post_handshake_auth.py
siotls/contents/handshakes/extensions/pre_shared_key.py
siotls/contents/handshakes/extensions/psk_key_exchange_modes.py
siotls/contents/handshakes/extensions/server_name.py
siotls/contents/handshakes/extensions/signature_algorithms.py
siotls/contents/handshakes/extensions/signed_certificate_timestamp.py
siotls/contents/handshakes/extensions/status_request.py
siotls/contents/handshakes/extensions/supported_groups.py
siotls-0.0.5.dist-info/licenses/LICENSE
siotls-0.0.5.dist-info/licenses/LICENSE.APACHE
siotls-0.0.5.dist-info/licenses/LICENSE.BSD
siotls-0.0.5.dist-info/METADATA
siotls-0.0.5.dist-info/WHEEL
siotls-0.0.5.dist-info/entry_points.txt
siotls-0.0.5.dist-info/top_level.txt
siotls-0.0.5.dist-info/RECORD
