Metadata-Version: 2.4
Name: siotls
Version: 0.0.5
Summary: Sans-IO Python implementation of the TLS 1.3 (RFC 8446) protocol stack
Author-email: Julien Castiaux <julien.castiaux@mailfence.com>
License-Expression: Apache-2.0 OR BSD-3-Clause
Project-URL: Homepage, https://codeberg.org/drlazor8/siotls
Project-URL: Download, https://pypi.org/simple/siotls/
Project-URL: Documentation, https://siotls.readthedocs.io/en/stable/index.html
Classifier: Development Status :: 3 - Alpha
Classifier: Environment :: No Input/Output (Daemon)
Classifier: Intended Audience :: Developers
Classifier: Operating System :: OS Independent
Classifier: Programming Language :: Python :: 3
Classifier: Topic :: Internet
Classifier: Topic :: Security
Classifier: Typing :: Typed
Requires-Python: >=3.11
License-File: LICENSE
License-File: LICENSE.APACHE
License-File: LICENSE.BSD
Requires-Dist: asn1crypto
Requires-Dist: idna
Provides-Extra: openssl
Requires-Dist: cryptography>=45; extra == "openssl"
Provides-Extra: hacl
Requires-Dist: pyhacl; extra == "hacl"
Dynamic: license-file
